bplustree/__init__.py
bplustree/const.py
bplustree/entry.py
bplustree/memory.py
bplustree/node.py
bplustree/serializer.py
bplustree/tree.py
bplustree/utils.py
bplustree-0.0.3.dist-info/DESCRIPTION.rst
bplustree-0.0.3.dist-info/METADATA
bplustree-0.0.3.dist-info/RECORD
bplustree-0.0.3.dist-info/WHEEL
bplustree-0.0.3.dist-info/metadata.json
bplustree-0.0.3.dist-info/top_level.txt
