Metadata-Version: 1.1
Name: bplustree
Version: 0.0.3
Summary: On-disk B+tree for Python 3
Home-page: https://github.com/NicolasLM/bplustree
Author: Nicolas Le Manchet
Author-email: nicolas@lemanchet.fr
License: MIT
Keywords: bplustree B+tree Btree database index
Platform: UNKNOWN
Classifier: Development Status :: 4 - Beta
Classifier: Intended Audience :: Developers
Classifier: Topic :: Software Development :: Libraries
Classifier: Topic :: Database
Classifier: License :: OSI Approved :: MIT License
Classifier: Natural Language :: English
Classifier: Programming Language :: Python :: 3
Classifier: Programming Language :: Python :: 3 :: Only
Classifier: Programming Language :: Python :: 3.5
Classifier: Programming Language :: Python :: 3.6
